[
    {
        "name": "My Day",
        "items": [
            {
                "title": "Be Silly!",
                "desc": "reach 500 silliness points",
                "dueDate": "tomorrow",
                "prio": 2,
                "notes": "Try doing something wacky"
            },
            {
                "title": "Be GOOFY!",
                "desc": "reach 500 goofiness points",
                "dueDate": "thursday",
                "prio": 2,
                "notes": "Try doing something spontaneous"
            }
        ]
    },
    {
        "name": "Grocery",
        "items": [
            {
                "title": "Eggs",
                "desc": "Buy a dozen brown eggs",
                "dueDate": "tomorrow",
                "prio": 2,
                "notes": "HEB"
            },
            {
                "title": "Milk",
                "desc": "Buy 2% milk, store brand",
                "dueDate": "tomorrow",
                "prio": 2,
                "notes": "Make sure we have 2 weeks before expiry"
            }
        ]
    }
]